addereq/EQT.cpython-313-aarch64-linux-musl.so
addereq/__init__.py
addereq/cleaning.cp310-win_amd64.pyd
addereq/cleaning.cpython-313-aarch64-linux-musl.so
addereq/fetching.cp310-win_amd64.pyd
addereq/fetching.cpython-313-aarch64-linux-musl.so
addereq/logger_config.cp310-win_amd64.pyd
addereq/logger_config.cpython-313-aarch64-linux-musl.so
addereq/plotting.cp310-win_amd64.pyd
addereq/plotting.cpython-313-aarch64-linux-musl.so
addereq-1.3.6.dist-info/METADATA
addereq-1.3.6.dist-info/WHEEL
addereq-1.3.6.dist-info/top_level.txt
addereq-1.3.6.dist-info/RECORD
addereq-1.3.6.dist-info/licenses/LICENSE
