Metadata-Version: 2.1
Name: addereq
Version: 1.3.6
Summary: 地震前兆数据自动处理框架
Author-email: WANG Qinglin <chd_wql@qq.com>
License: MIT License
Classifier: Programming Language :: Python :: 3
Classifier: Programming Language :: Python :: 3.8
Classifier: Programming Language :: Python :: 3.9
Classifier: Programming Language :: Python :: 3.10
Classifier: Programming Language :: Python :: 3.11
Classifier: Programming Language :: Python :: 3.12
Classifier: Programming Language :: Python :: 3.13
Requires-Python: >=3.8
License-File: LICENSE
Requires-Dist: pymysql
Requires-Dist: cx-Oracle
Requires-Dist: matplotlib
Requires-Dist: numpy
Requires-Dist: openpyxl
Requires-Dist: pandas
Requires-Dist: scipy
Requires-Dist: seaborn
Requires-Dist: SQLAlchemy==1.4.48
Requires-Dist: python-pptx
Requires-Dist: python-docx
